[
  {
    "date": "2025-03-22",
    "company": "Facebook",
    "avg_sentiment": 0.38451,
    "num_comments": 849,
    "num_posts": 10
  },
  {
    "date": "2025-03-27",
    "company": "Facebook",
    "avg_sentiment": -0.24219999999999997,
    "num_comments": 171,
    "num_posts": 6
  },
  {
    "date": "2025-03-31",
    "company": "Facebook",
    "avg_sentiment": 0.35776666666666673,
    "num_comments": 246,
    "num_posts": 3
  },
  {
    "date": "2025-04-05",
    "company": "Facebook",
    "avg_sentiment": 0.2912444444444444,
    "num_comments": 570,
    "num_posts": 9
  },
  {
    "date": "2025-04-08",
    "company": "Facebook",
    "avg_sentiment": 0.97305,
    "num_comments": 187,
    "num_posts": 2
  },
  {
    "date": "2025-04-12",
    "company": "Facebook",
    "avg_sentiment": 0.7443500000000001,
    "num_comments": 115,
    "num_posts": 2
  }
]